treescope/__init__.py
treescope/canonical_aliases.py
treescope/context.py
treescope/dataclass_util.py
treescope/dtype_util.py
treescope/figures.py
treescope/formatting_util.py
treescope/handlers.py
treescope/layout_algorithms.py
treescope/lowering.py
treescope/ndarray_adapters.py
treescope/renderers.py
treescope/rendering_parts.py
treescope/repr_lib.py
treescope/type_registries.py
treescope/_internal/__init__.py
treescope/_internal/arrayviz_impl.py
treescope/_internal/docs_util.py
treescope/_internal/figures_impl.py
treescope/_internal/html_encapsulation.py
treescope/_internal/html_escaping.py
treescope/_internal/object_inspection.py
treescope/_internal/api/__init__.py
treescope/_internal/api/array_autovisualizer.py
treescope/_internal/api/arrayviz.py
treescope/_internal/api/autovisualize.py
treescope/_internal/api/default_renderer.py
treescope/_internal/api/ipython_integration.py
treescope/_internal/handlers/__init__.py
treescope/_internal/handlers/autovisualizer_hook.py
treescope/_internal/handlers/basic_types_handler.py
treescope/_internal/handlers/canonical_alias_postprocessor.py
treescope/_internal/handlers/custom_type_handlers.py
treescope/_internal/handlers/function_reflection_handlers.py
treescope/_internal/handlers/generic_pytree_handler.py
treescope/_internal/handlers/generic_repr_handler.py
treescope/_internal/handlers/repr_html_postprocessor.py
treescope/_internal/handlers/shared_value_postprocessor.py
treescope/_internal/js/arrayviz.js
treescope/_internal/parts/__init__.py
treescope/_internal/parts/basic_parts.py
treescope/_internal/parts/common_structures.py
treescope/_internal/parts/common_styles.py
treescope/_internal/parts/custom_dataclass_util.py
treescope/_internal/parts/embedded_iframe.py
treescope/_internal/parts/foldable_impl.py
treescope/_internal/parts/part_interface.py
treescope/external/__init__.py
treescope/external/jax_support.py
treescope/external/numpy_support.py
treescope/external/torch_support.py
treescope-0.1.8.dist-info/LICENSE
treescope-0.1.8.dist-info/WHEEL
treescope-0.1.8.dist-info/METADATA
treescope-0.1.8.dist-info/RECORD
