Metadata-Version: 2.3
Name: treescope
Version: 0.1.8
Summary: Treescope: An interactive HTML pretty-printer for ML research in IPython notebooks.
Keywords: 
Author-email: The Treescope Authors <treescope-dev@google.com>
Requires-Python: >=3.10
Classifier: Programming Language :: Python :: 3
Classifier: Programming Language :: Python :: 3 :: Only
Classifier: License :: OSI Approved :: Apache Software License
Classifier: Intended Audience :: Science/Research
Requires-Dist: numpy>=1.25.2
Requires-Dist: pylint>=2.6.0 ; extra == "dev"
Requires-Dist: pyink>=24.3.0 ; extra == "dev"
Requires-Dist: ipython ; extra == "dev"
Requires-Dist: jupyter ; extra == "dev"
Requires-Dist: pytest>=8.2.2 ; extra == "dev"
Requires-Dist: pytype ; extra == "dev"
Requires-Dist: ipython ; extra == "docs"
Requires-Dist: sphinx>=6.0.0,<7.3.0 ; extra == "docs"
Requires-Dist: sphinx-book-theme>=1.0.1 ; extra == "docs"
Requires-Dist: sphinxcontrib-katex ; extra == "docs"
Requires-Dist: ipython>=8.8.0 ; extra == "docs"
Requires-Dist: jax[cpu]>=0.4.23 ; extra == "docs"
Requires-Dist: myst-nb>=1.0.0 ; extra == "docs"
Requires-Dist: myst-parser>=3.0.1 ; extra == "docs"
Requires-Dist: matplotlib>=3.5.0 ; extra == "docs"
Requires-Dist: packaging==24.1 ; extra == "docs"
Requires-Dist: palettable==3.3.3 ; extra == "docs"
Requires-Dist: pandas==2.2.2 ; extra == "docs"
Requires-Dist: plotly==5.22.0 ; extra == "docs"
Requires-Dist: penzai~=0.2.4 ; extra == "docs"
Requires-Dist: sphinx_contributors ; extra == "docs"
Requires-Dist: sphinx-hoverxref ; extra == "docs"
Requires-Dist: torch==2.3.1 ; extra == "docs"
Requires-Dist: ipython ; extra == "notebook"
Requires-Dist: palettable ; extra == "notebook"
Requires-Dist: jax>=0.4.23 ; extra == "notebook"
Requires-Dist: absl-py>=1.4.0 ; extra == "test"
Requires-Dist: jax>=0.4.23 ; extra == "test"
Requires-Dist: pytest>=8.2.2 ; extra == "test"
Requires-Dist: torch>=2.0.0 ; extra == "test"
Project-URL: homepage, https://github.com/google-deepmind/treescope
Project-URL: repository, https://github.com/google-deepmind/treescope
Provides-Extra: dev
Provides-Extra: docs
Provides-Extra: notebook
Provides-Extra: test
